<?xml version="1.0" encoding="utf-8"?>
<Deployment xmlns="http://schemas.microsoft.com/windowsphone/2012/deployment" AppPlatformVersion="8.0">
  <DefaultLanguage xmlns="" code="en-US" />
  <Languages xmlns="">
    <Language code="en" />
    <Language code="ro" />
  </Languages>
  <App xmlns="" ProductID="{60aa88d5-8659-4680-907b-55d9445d2b8e}" Title="TrackMyTrails" RuntimeType="Silverlight" Version="1.0.0.0" Genre="apps.normal" Author="stonemonkey77ro author" Description="Design to record and track walking, running and cycling activities. " Publisher="stonemonkey77ro" PublisherID="{58519517-d8a9-4762-b6c9-d104bfec84ee}">
    <IconPath IsRelative="true" IsResource="false">Assets\ApplicationIcon.png</IconPath>
    <Capabilities>
      <Capability Name="ID_CAP_NETWORKING" />
      <Capability Name="ID_CAP_MEDIALIB_AUDIO" />
      <Capability Name="ID_CAP_MEDIALIB_PLAYBACK" />
      <Capability Name="ID_CAP_SENSORS" />
      <Capability Name="ID_CAP_WEBBROWSERCOMPONENT" />
    </Capabilities>
    <Tasks>
      <DefaultTask Name="_default" NavigationPage="/Components/MainPage/MainPageView.xaml" />
    </Tasks>
    <Tokens>
      <PrimaryToken TokenID="TrackMyTrailsToken" TaskName="_default">
        <TemplateFlip>
          <SmallImageURI IsRelative="true" IsResource="false">Assets\Tiles\FlipCycleTileSmall.png</SmallImageURI>
          <Count>0</Count>
          <BackgroundImageURI IsRelative="true" IsResource="false">Assets\Tiles\FlipCycleTileMedium.png</BackgroundImageURI>
          <Title>TrackMyTrails</Title>
          <BackContent>
          </BackContent>
          <BackBackgroundImageURI>
          </BackBackgroundImageURI>
          <BackTitle>
          </BackTitle>
          <DeviceLockImageURI>
          </DeviceLockImageURI>
          <HasLarge>
          </HasLarge>
        </TemplateFlip>
      </PrimaryToken>
    </Tokens>
    <ScreenResolutions>
      <ScreenResolution Name="ID_RESOLUTION_WVGA" />
      <ScreenResolution Name="ID_RESOLUTION_WXGA" />
      <ScreenResolution Name="ID_RESOLUTION_HD720P" />
    </ScreenResolutions>
  </App>
</Deployment>